[
  {
    "fiyat": "11 USD",
    "havayolu": "Wizz Air",
    "zamanaralik": "9:25pm -\n11:35pm",
    "tarih": "4 Eylül 2024, Çarşamba",
    "sure": "2 saat 10 dakika",
    "guzergah": "Malmö (MMX) →\nBelgrade (BEG)",
    "direkt": "Direct"
  },
  {
    "fiyat": "13.97 USD",
    "havayolu": "Ryanair UK",
    "zamanaralik": "9:50pm -\n10:45pm",
    "tarih": "12 Ağustos 2024, Pazartesi",
    "sure": "1 saat 55 dakika",
    "guzergah": "Oslo (TRF) →\nLondon (STN)",
    "direkt": "Direct"
  },
  {
    "fiyat": "13.97 USD",
    "havayolu": "Ryanair UK",
    "zamanaralik": "10:15am -\n11:25am",
    "tarih": "9 Eylül 2024, Pazartesi",
    "sure": "2 saat 10 dakika",
    "guzergah": "Oslo (OSL) →\nLondon (STN)",
    "direkt": "Direct"
  },
  {
    "fiyat": "14.64 USD",
    "havayolu": "Ryanair",
    "zamanaralik": "10:50am -\n11:50am",
    "tarih": "7 Eylül 2024, Cumartesi",
    "sure": "2 saat 0 dakika",
    "guzergah": "Gothenburg (GOT) →\nManchester (MAN)",
    "direkt": "Direct"
  },
  {
    "fiyat": "14.64 USD",
    "havayolu": "Ryanair",
    "zamanaralik": "8:30pm -\n9:30pm",
    "tarih": "8 Eylül 2024, Pazar",
    "sure": "2 saat 0 dakika",
    "guzergah": "Gothenburg (GOT) →\nLondon (STN)",
    "direkt": "Direct"
  },
  {
    "fiyat": "14.64 USD",
    "havayolu": "Ryanair",
    "zamanaralik": "10:15pm -\n11:15pm",
    "tarih": "6 Eylül 2024, Cuma",
    "sure": "2 saat 0 dakika",
    "guzergah": "Gothenburg (GOT) →\nManchester (MAN)",
    "direkt": "Direct"
  },
  {
    "fiyat": "14.64 USD",
    "havayolu": "Ryanair",
    "zamanaralik": "3:10pm -\n4:10pm",
    "tarih": "9 Eylül 2024, Pazartesi",
    "sure": "2 saat 0 dakika",
    "guzergah": "Gothenburg (GOT) →\nLondon (STN)",
    "direkt": "Direct"
  },
  {
    "fiyat": "14.64 USD",
    "havayolu": "Ryanair",
    "zamanaralik": "10:50am -\n12:00pm",
    "tarih": "13 Ağustos 2024, Salı",
    "sure": "2 saat 10 dakika",
    "guzergah": "Örebro (ORB) →\nLondon (STN)",
    "direkt": "Direct"
  },
  {
    "fiyat": "14.64 USD",
    "havayolu": "Ryanair",
    "zamanaralik": "3:50pm -\n5:00pm",
    "tarih": "7 Eylül 2024, Cumartesi",
    "sure": "2 saat 10 dakika",
    "guzergah": "Örebro (ORB) →\nLondon (STN)",
    "direkt": "Direct"
  },
  {
    "fiyat": "14.64 USD",
    "havayolu": "Ryanair",
    "zamanaralik": "5:45am -\n8:55am",
    "tarih": "18 Ağustos 2024, Pazar",
    "sure": "3 saat 10 dakika",
    "guzergah": "Stockholm (ARN) →\nTirana (TIA)",
    "direkt": "Direct"
  },
  {
    "fiyat": "15 USD",
    "havayolu": "Wizz Air Malta",
    "zamanaralik": "8:20am -\n9:15am",
    "tarih": "4 Eylül 2024, Çarşamba",
    "sure": "0 saat 55 dakika",
    "guzergah": "Bari (BRI) →\nTirana (TIA)",
    "direkt": "Direct"
  },
  {
    "fiyat": "15 USD",
    "havayolu": "Wizz Air Malta",
    "zamanaralik": "7:55am -\n8:50am",
    "tarih": "9 Eylül 2024, Pazartesi",
    "sure": "0 saat 55 dakika",
    "guzergah": "Bari (BRI) →\nTirana (TIA)",
    "direkt": "Direct"
  },
  {
    "fiyat": "15 USD",
    "havayolu": "Wizz Air Malta",
    "zamanaralik": "1:40pm -\n2:35pm",
    "tarih": "28 Ağustos 2024, Çarşamba",
    "sure": "0 saat 55 dakika",
    "guzergah": "Brindisi (BDS) →\nTirana (TIA)",
    "direkt": "Direct"
  },
  {
    "fiyat": "15 USD",
    "havayolu": "Wizz Air Malta",
    "zamanaralik": "7:40am -\n8:35am",
    "tarih": "30 Ağustos 2024, Cuma",
    "sure": "0 saat 55 dakika",
    "guzergah": "Bari (BRI) →\nTirana (TIA)",
    "direkt": "Direct"
  },
  {
    "fiyat": "15 USD",
    "havayolu": "Wizz Air Malta",
    "zamanaralik": "8:30am -\n9:25am",
    "tarih": "27 Ağustos 2024, Salı",
    "sure": "0 saat 55 dakika",
    "guzergah": "Bari (BRI) →\nTirana (TIA)",
    "direkt": "Direct"
  },
  {
    "fiyat": "15 USD",
    "havayolu": "Wizz Air Malta",
    "zamanaralik": "12:50pm -\n1:45pm",
    "tarih": "3 Eylül 2024, Salı",
    "sure": "0 saat 55 dakika",
    "guzergah": "Bari (BRI) →\nTirana (TIA)",
    "direkt": "Direct"
  },
  {
    "fiyat": "15 USD",
    "havayolu": "Wizz Air Malta",
    "zamanaralik": "8:25am -\n9:20am",
    "tarih": "25 Ağustos 2024, Pazar",
    "sure": "0 saat 55 dakika",
    "guzergah": "Bari (BRI) →\nTirana (TIA)",
    "direkt": "Direct"
  },
  {
    "fiyat": "15 USD",
    "havayolu": "Wizz Air Malta",
    "zamanaralik": "12:50pm -\n1:45pm",
    "tarih": "4 Eylül 2024, Çarşamba",
    "sure": "0 saat 55 dakika",
    "guzergah": "Bari (BRI) →\nTirana (TIA)",
    "direkt": "Direct"
  },
  {
    "fiyat": "15 USD",
    "havayolu": "Wizz Air Malta",
    "zamanaralik": "12:55pm -\n1:50pm",
    "tarih": "6 Eylül 2024, Cuma",
    "sure": "0 saat 55 dakika",
    "guzergah": "Bari (BRI) →\nTirana (TIA)",
    "direkt": "Direct"
  },
  {
    "fiyat": "15 USD",
    "havayolu": "Wizz Air Malta",
    "zamanaralik": "1:05pm -\n2:00pm",
    "tarih": "5 Eylül 2024, Perşembe",
    "sure": "0 saat 55 dakika",
    "guzergah": "Bari (BRI) →\nTirana (TIA)",
    "direkt": "Direct"
  },
  {
    "fiyat": "15 USD",
    "havayolu": "Wizz Air Malta",
    "zamanaralik": "7:40am -\n8:35am",
    "tarih": "23 Ağustos 2024, Cuma",
    "sure": "0 saat 55 dakika",
    "guzergah": "Bari (BRI) →\nTirana (TIA)",
    "direkt": "Direct"
  },
  {
    "fiyat": "15 USD",
    "havayolu": "Wizz Air Malta",
    "zamanaralik": "8:30am -\n9:25am",
    "tarih": "3 Eylül 2024, Salı",
    "sure": "0 saat 55 dakika",
    "guzergah": "Bari (BRI) →\nTirana (TIA)",
    "direkt": "Direct"
  },
  {
    "fiyat": "15 USD",
    "havayolu": "Wizz Air Malta",
    "zamanaralik": "7:35am -\n8:30am",
    "tarih": "6 Eylül 2024, Cuma",
    "sure": "0 saat 55 dakika",
    "guzergah": "Bari (BRI) →\nTirana (TIA)",
    "direkt": "Direct"
  },
  {
    "fiyat": "15 USD",
    "havayolu": "Wizz Air Malta",
    "zamanaralik": "8:25am -\n9:20am",
    "tarih": "29 Ağustos 2024, Perşembe",
    "sure": "0 saat 55 dakika",
    "guzergah": "Bari (BRI) →\nTirana (TIA)",
    "direkt": "Direct"
  },
  {
    "fiyat": "15 USD",
    "havayolu": "Wizz Air Malta",
    "zamanaralik": "8:25am -\n9:20am",
    "tarih": "8 Eylül 2024, Pazar",
    "sure": "0 saat 55 dakika",
    "guzergah": "Bari (BRI) →\nTirana (TIA)",
    "direkt": "Direct"
  },
  {
    "fiyat": "15 USD",
    "havayolu": "Wizz Air Malta",
    "zamanaralik": "1:15pm -\n2:10pm",
    "tarih": "7 Eylül 2024, Cumartesi",
    "sure": "0 saat 55 dakika",
    "guzergah": "Bari (BRI) →\nTirana (TIA)",
    "direkt": "Direct"
  },
  {
    "fiyat": "15 USD",
    "havayolu": "Wizz Air Malta",
    "zamanaralik": "1:05pm -\n2:00pm",
    "tarih": "29 Ağustos 2024, Perşembe",
    "sure": "0 saat 55 dakika",
    "guzergah": "Bari (BRI) →\nTirana (TIA)",
    "direkt": "Direct"
  },
  {
    "fiyat": "15 USD",
    "havayolu": "Wizz Air Malta",
    "zamanaralik": "8:20am -\n9:15am",
    "tarih": "28 Ağustos 2024, Çarşamba",
    "sure": "0 saat 55 dakika",
    "guzergah": "Bari (BRI) →\nTirana (TIA)",
    "direkt": "Direct"
  },
  {
    "fiyat": "15 USD",
    "havayolu": "Wizz Air Malta",
    "zamanaralik": "8:25am -\n9:20am",
    "tarih": "5 Eylül 2024, Perşembe",
    "sure": "0 saat 55 dakika",
    "guzergah": "Bari (BRI) →\nTirana (TIA)",
    "direkt": "Direct"
  },
  {
    "fiyat": "15 USD",
    "havayolu": "Wizz Air Malta",
    "zamanaralik": "5:55pm -\n7:25pm",
    "tarih": "19 Ağustos 2024, Pazartesi",
    "sure": "1 saat 30 dakika",
    "guzergah": "Venice (TSF) →\nTirana (TIA)",
    "direkt": "Direct"
  },
  {
    "fiyat": "15.96 USD",
    "havayolu": "Ryanair",
    "zamanaralik": "10:10pm -\n10:00pm",
    "tarih": "29 Ağustos 2024, Perşembe",
    "sure": "0 saat 50 dakika",
    "guzergah": "Málaga (AGP) →\nTangier (TNG)",
    "direkt": "Direct"
  },
  {
    "fiyat": "15.96 USD",
    "havayolu": "Ryanair",
    "zamanaralik": "6:35am -\n6:25am",
    "tarih": "19 Ağustos 2024, Pazartesi",
    "sure": "0 saat 50 dakika",
    "guzergah": "Málaga (AGP) →\nTangier (TNG)",
    "direkt": "Direct"
  },
  {
    "fiyat": "15.96 USD",
    "havayolu": "Ryanair",
    "zamanaralik": "6:35am -\n6:25am",
    "tarih": "9 Eylül 2024, Pazartesi",
    "sure": "0 saat 50 dakika",
    "guzergah": "Málaga (AGP) →\nTangier (TNG)",
    "direkt": "Direct"
  },
  {
    "fiyat": "15.96 USD",
    "havayolu": "Ryanair",
    "zamanaralik": "10:10pm -\n10:00pm",
    "tarih": "22 Ağustos 2024, Perşembe",
    "sure": "0 saat 50 dakika",
    "guzergah": "Málaga (AGP) →\nTangier (TNG)",
    "direkt": "Direct"
  },
  {
    "fiyat": "15.96 USD",
    "havayolu": "Ryanair",
    "zamanaralik": "10:10pm -\n10:00pm",
    "tarih": "5 Eylül 2024, Perşembe",
    "sure": "0 saat 50 dakika",
    "guzergah": "Málaga (AGP) →\nTangier (TNG)",
    "direkt": "Direct"
  },
  {
    "fiyat": "15.96 USD",
    "havayolu": "Ryanair",
    "zamanaralik": "6:35am -\n6:25am",
    "tarih": "2 Eylül 2024, Pazartesi",
    "sure": "0 saat 50 dakika",
    "guzergah": "Málaga (AGP) →\nTangier (TNG)",
    "direkt": "Direct"
  },
  {
    "fiyat": "15.96 USD",
    "havayolu": "Ryanair",
    "zamanaralik": "9:50pm -\n9:40pm",
    "tarih": "28 Ağustos 2024, Çarşamba",
    "sure": "0 saat 50 dakika",
    "guzergah": "Málaga (AGP) →\nTangier (TNG)",
    "direkt": "Direct"
  },
  {
    "fiyat": "15.96 USD",
    "havayolu": "Ryanair",
    "zamanaralik": "10:10pm -\n10:05pm",
    "tarih": "19 Ağustos 2024, Pazartesi",
    "sure": "0 saat 55 dakika",
    "guzergah": "Málaga (AGP) →\nNador (NDR)",
    "direkt": "Direct"
  },
  {
    "fiyat": "15.96 USD",
    "havayolu": "Ryanair",
    "zamanaralik": "10:10pm -\n10:05pm",
    "tarih": "9 Eylül 2024, Pazartesi",
    "sure": "0 saat 55 dakika",
    "guzergah": "Málaga (AGP) →\nNador (NDR)",
    "direkt": "Direct"
  },
  {
    "fiyat": "15.96 USD",
    "havayolu": "Ryanair",
    "zamanaralik": "10:25pm -\n10:20pm",
    "tarih": "21 Ağustos 2024, Çarşamba",
    "sure": "0 saat 55 dakika",
    "guzergah": "Málaga (AGP) →\nNador (NDR)",
    "direkt": "Direct"
  },
  {
    "fiyat": "15.96 USD",
    "havayolu": "Ryanair",
    "zamanaralik": "10:10pm -\n10:05pm",
    "tarih": "26 Ağustos 2024, Pazartesi",
    "sure": "0 saat 55 dakika",
    "guzergah": "Málaga (AGP) →\nNador (NDR)",
    "direkt": "Direct"
  },
  {
    "fiyat": "15.96 USD",
    "havayolu": "Ryanair",
    "zamanaralik": "10:25pm -\n10:20pm",
    "tarih": "28 Ağustos 2024, Çarşamba",
    "sure": "0 saat 55 dakika",
    "guzergah": "Málaga (AGP) →\nNador (NDR)",
    "direkt": "Direct"
  },
  {
    "fiyat": "15.96 USD",
    "havayolu": "Ryanair",
    "zamanaralik": "10:25pm -\n10:20pm",
    "tarih": "4 Eylül 2024, Çarşamba",
    "sure": "0 saat 55 dakika",
    "guzergah": "Málaga (AGP) →\nNador (NDR)",
    "direkt": "Direct"
  },
  {
    "fiyat": "15.96 USD",
    "havayolu": "Ryanair",
    "zamanaralik": "10:10pm -\n10:05pm",
    "tarih": "2 Eylül 2024, Pazartesi",
    "sure": "0 saat 55 dakika",
    "guzergah": "Málaga (AGP) →\nNador (NDR)",
    "direkt": "Direct"
  },
  {
    "fiyat": "15.96 USD",
    "havayolu": "Ryanair",
    "zamanaralik": "1:45pm -\n2:45pm",
    "tarih": "8 Eylül 2024, Pazar",
    "sure": "1 saat 0 dakika",
    "guzergah": "Bari (BRI) →\nTirana (TIA)",
    "direkt": "Direct"
  },
  {
    "fiyat": "15.96 USD",
    "havayolu": "Ryanair",
    "zamanaralik": "6:20am -\n7:20am",
    "tarih": "9 Eylül 2024, Pazartesi",
    "sure": "1 saat 0 dakika",
    "guzergah": "Bari (BRI) →\nTirana (TIA)",
    "direkt": "Direct"
  },
  {
    "fiyat": "15.96 USD",
    "havayolu": "Ryanair",
    "zamanaralik": "6:50pm -\n7:50pm",
    "tarih": "7 Eylül 2024, Cumartesi",
    "sure": "1 saat 0 dakika",
    "guzergah": "Bari (BRI) →\nTirana (TIA)",
    "direkt": "Direct"
  },
  {
    "fiyat": "15.96 USD",
    "havayolu": "Ryanair",
    "zamanaralik": "10:45am -\n10:50am",
    "tarih": "8 Eylül 2024, Pazar",
    "sure": "1 saat 5 dakika",
    "guzergah": "Eindhoven (EIN) →\nLondon (STN)",
    "direkt": "Direct"
  },
  {
    "fiyat": "15.96 USD",
    "havayolu": "Ryanair",
    "zamanaralik": "10:30am -\n10:35am",
    "tarih": "9 Eylül 2024, Pazartesi",
    "sure": "1 saat 5 dakika",
    "guzergah": "Eindhoven (EIN) →\nLondon (STN)",
    "direkt": "Direct"
  },
  {
    "fiyat": "15.96 USD",
    "havayolu": "Ryanair",
    "zamanaralik": "2:10pm -\n2:15pm",
    "tarih": "6 Eylül 2024, Cuma",
    "sure": "1 saat 5 dakika",
    "guzergah": "Eindhoven (EIN) →\nLondon (STN)",
    "direkt": "Direct"
  },
  {
    "fiyat": "15.96 USD",
    "havayolu": "Ryanair",
    "zamanaralik": "11:50am -\n11:55am",
    "tarih": "6 Eylül 2024, Cuma",
    "sure": "1 saat 5 dakika",
    "guzergah": "Eindhoven (EIN) →\nLondon (STN)",
    "direkt": "Direct"
  },
  {
    "fiyat": "15.96 USD",
    "havayolu": "Ryanair",
    "zamanaralik": "9:45pm -\n11:00pm",
    "tarih": "6 Eylül 2024, Cuma",
    "sure": "1 saat 15 dakika",
    "guzergah": "Lisbon (LIS) →\nTangier (TNG)",
    "direkt": "Direct"
  },
  {
    "fiyat": "15.96 USD",
    "havayolu": "Ryanair",
    "zamanaralik": "3:40pm -\n3:55pm",
    "tarih": "6 Eylül 2024, Cuma",
    "sure": "1 saat 15 dakika",
    "guzergah": "Luxembourg (LUX) →\nLondon (STN)",
    "direkt": "Direct"
  },
  {
    "fiyat": "15.96 USD",
    "havayolu": "Ryanair",
    "zamanaralik": "4:55pm -\n5:10pm",
    "tarih": "9 Eylül 2024, Pazartesi",
    "sure": "1 saat 15 dakika",
    "guzergah": "Luxembourg (LUX) →\nLondon (STN)",
    "direkt": "Direct"
  },
  {
    "fiyat": "15.96 USD",
    "havayolu": "Ryanair",
    "zamanaralik": "10:10pm -\n10:30pm",
    "tarih": "6 Eylül 2024, Cuma",
    "sure": "1 saat 20 dakika",
    "guzergah": "Cologne (CGN) →\nLondon (STN)",
    "direkt": "Direct"
  },
  {
    "fiyat": "15.96 USD",
    "havayolu": "Ryanair",
    "zamanaralik": "7:15pm -\n7:40pm",
    "tarih": "7 Eylül 2024, Cumartesi",
    "sure": "1 saat 25 dakika",
    "guzergah": "Nantes (NTE) →\nLondon (STN)",
    "direkt": "Direct"
  },
  {
    "fiyat": "15.96 USD",
    "havayolu": "Ryanair",
    "zamanaralik": "7:40pm -\n9:05pm",
    "tarih": "13 Ağustos 2024, Salı",
    "sure": "1 saat 25 dakika",
    "guzergah": "Faro (FAO) →\nMarrakesh (RAK)",
    "direkt": "Direct"
  },
  {
    "fiyat": "15.96 USD",
    "havayolu": "Ryanair",
    "zamanaralik": "4:40pm -\n6:05pm",
    "tarih": "7 Eylül 2024, Cumartesi",
    "sure": "1 saat 25 dakika",
    "guzergah": "Rome (CIA) →\nTirana (TIA)",
    "direkt": "Direct"
  },
  {
    "fiyat": "15.96 USD",
    "havayolu": "Ryanair",
    "zamanaralik": "11:35am -\n12:00pm",
    "tarih": "6 Eylül 2024, Cuma",
    "sure": "1 saat 25 dakika",
    "guzergah": "Tours (TUF) →\nLondon (STN)",
    "direkt": "Direct"
  },
  {
    "fiyat": "15.96 USD",
    "havayolu": "Ryanair",
    "zamanaralik": "2:05pm -\n2:30pm",
    "tarih": "8 Eylül 2024, Pazar",
    "sure": "1 saat 25 dakika",
    "guzergah": "Seville (SVQ) →\nMarrakesh (RAK)",
    "direkt": "Direct"
  },
  {
    "fiyat": "15.96 USD",
    "havayolu": "Ryanair",
    "zamanaralik": "9:35am -\n10:00am",
    "tarih": "7 Eylül 2024, Cumartesi",
    "sure": "1 saat 25 dakika",
    "guzergah": "Nantes (NTE) →\nLondon (STN)",
    "direkt": "Direct"
  },
  {
    "fiyat": "15.96 USD",
    "havayolu": "Ryanair",
    "zamanaralik": "9:05pm -\n9:30pm",
    "tarih": "9 Eylül 2024, Pazartesi",
    "sure": "1 saat 25 dakika",
    "guzergah": "Málaga (AGP) →\nMarrakesh (RAK)",
    "direkt": "Direct"
  },
  {
    "fiyat": "15.96 USD",
    "havayolu": "Ryanair",
    "zamanaralik": "11:50am -\n1:15pm",
    "tarih": "7 Eylül 2024, Cumartesi",
    "sure": "1 saat 25 dakika",
    "guzergah": "Rome (CIA) →\nTirana (TIA)",
    "direkt": "Direct"
  },
  {
    "fiyat": "15.96 USD",
    "havayolu": "Ryanair",
    "zamanaralik": "1:50pm -\n2:15pm",
    "tarih": "8 Eylül 2024, Pazar",
    "sure": "1 saat 25 dakika",
    "guzergah": "Málaga (AGP) →\nMarrakesh (RAK)",
    "direkt": "Direct"
  },
  {
    "fiyat": "15.96 USD",
    "havayolu": "Ryanair",
    "zamanaralik": "6:00pm -\n7:25pm",
    "tarih": "6 Eylül 2024, Cuma",
    "sure": "1 saat 25 dakika",
    "guzergah": "Rome (CIA) →\nTirana (TIA)",
    "direkt": "Direct"
  },
  {
    "fiyat": "15.96 USD",
    "havayolu": "Ryanair",
    "zamanaralik": "11:40am -\n1:05pm",
    "tarih": "6 Eylül 2024, Cuma",
    "sure": "1 saat 25 dakika",
    "guzergah": "Lanzarote (ACE) →\nMarrakesh (RAK)",
    "direkt": "Direct"
  },
  {
    "fiyat": "15.96 USD",
    "havayolu": "Ryanair",
    "zamanaralik": "9:05pm -\n9:30pm",
    "tarih": "19 Ağustos 2024, Pazartesi",
    "sure": "1 saat 25 dakika",
    "guzergah": "Málaga (AGP) →\nMarrakesh (RAK)",
    "direkt": "Direct"
  },
  {
    "fiyat": "15.96 USD",
    "havayolu": "Ryanair",
    "zamanaralik": "8:05am -\n9:30am",
    "tarih": "9 Eylül 2024, Pazartesi",
    "sure": "1 saat 25 dakika",
    "guzergah": "Lanzarote (ACE) →\nMarrakesh (RAK)",
    "direkt": "Direct"
  },
  {
    "fiyat": "15.96 USD",
    "havayolu": "Ryanair",
    "zamanaralik": "9:35pm -\n10:05pm",
    "tarih": "15 Ağustos 2024, Perşembe",
    "sure": "1 saat 30 dakika",
    "guzergah": "Bucharest (OTP) →\nTirana (TIA)",
    "direkt": "Direct"
  },
  {
    "fiyat": "15.96 USD",
    "havayolu": "Ryanair",
    "zamanaralik": "7:00am -\n7:35am",
    "tarih": "14 Ağustos 2024, Çarşamba",
    "sure": "1 saat 35 dakika",
    "guzergah": "Billund (BLL) →\nLondon (STN)",
    "direkt": "Direct"
  },
  {
    "fiyat": "16 USD",
    "havayolu": "Wizz Air Malta",
    "zamanaralik": "1:40pm -\n2:35pm",
    "tarih": "4 Eylül 2024, Çarşamba",
    "sure": "0 saat 55 dakika",
    "guzergah": "Brindisi (BDS) →\nTirana (TIA)",
    "direkt": "Direct"
  },
  {
    "fiyat": "16 USD",
    "havayolu": "Wizz Air Malta",
    "zamanaralik": "5:05pm -\n6:25pm",
    "tarih": "7 Eylül 2024, Cumartesi",
    "sure": "1 saat 20 dakika",
    "guzergah": "Rimini (RMI) →\nTirana (TIA)",
    "direkt": "Direct"
  },
  {
    "fiyat": "16 USD",
    "havayolu": "Wizz Air Malta",
    "zamanaralik": "3:35pm -\n5:05pm",
    "tarih": "18 Ağustos 2024, Pazar",
    "sure": "1 saat 30 dakika",
    "guzergah": "Venice (TSF) →\nTirana (TIA)",
    "direkt": "Direct"
  },
  {
    "fiyat": "16 USD",
    "havayolu": "Wizz Air Malta",
    "zamanaralik": "6:45pm -\n8:15pm",
    "tarih": "18 Ağustos 2024, Pazar",
    "sure": "1 saat 30 dakika",
    "guzergah": "Venice (TSF) →\nTirana (TIA)",
    "direkt": "Direct"
  },
  {
    "fiyat": "16.11 USD",
    "havayolu": "Ryanair",
    "zamanaralik": "9:15am -\n9:40am",
    "tarih": "15 Ağustos 2024, Perşembe",
    "sure": "1 saat 25 dakika",
    "guzergah": "Billund (BLL) →\nLondon (STN)",
    "direkt": "Direct"
  },
  {
    "fiyat": "16.11 USD",
    "havayolu": "Ryanair",
    "zamanaralik": "7:30pm -\n8:05pm",
    "tarih": "13 Ağustos 2024, Salı",
    "sure": "1 saat 35 dakika",
    "guzergah": "Billund (BLL) →\nLondon (STN)",
    "direkt": "Direct"
  },
  {
    "fiyat": "16.11 USD",
    "havayolu": "Ryanair",
    "zamanaralik": "1:05pm -\n1:40pm",
    "tarih": "13 Ağustos 2024, Salı",
    "sure": "1 saat 35 dakika",
    "guzergah": "Billund (BLL) →\nLondon (STN)",
    "direkt": "Direct"
  },
  {
    "fiyat": "16.11 USD",
    "havayolu": "Ryanair",
    "zamanaralik": "9:45pm -\n10:20pm",
    "tarih": "13 Ağustos 2024, Salı",
    "sure": "1 saat 35 dakika",
    "guzergah": "Billund (BLL) →\nLondon (STN)",
    "direkt": "Direct"
  },
  {
    "fiyat": "16.28 USD",
    "havayolu": "Ryanair",
    "zamanaralik": "3:05pm -\n3:00pm",
    "tarih": "6 Eylül 2024, Cuma",
    "sure": "0 saat 55 dakika",
    "guzergah": "Málaga (AGP) →\nNador (NDR)",
    "direkt": "Direct"
  },
  {
    "fiyat": "17.36 USD",
    "havayolu": "Ryanair",
    "zamanaralik": "6:20pm -\n6:25pm",
    "tarih": "7 Eylül 2024, Cumartesi",
    "sure": "1 saat 5 dakika",
    "guzergah": "Eindhoven (EIN) →\nLondon (STN)",
    "direkt": "Direct"
  },
  {
    "fiyat": "18 USD",
    "havayolu": "Ryanair",
    "zamanaralik": "6:20am -\n7:20am",
    "tarih": "19 Ağustos 2024, Pazartesi",
    "sure": "1 saat 0 dakika",
    "guzergah": "Bari (BRI) →\nTirana (TIA)",
    "direkt": "Direct"
  },
  {
    "fiyat": "18 USD",
    "havayolu": "Ryanair",
    "zamanaralik": "9:20pm -\n9:25pm",
    "tarih": "7 Eylül 2024, Cumartesi",
    "sure": "1 saat 5 dakika",
    "guzergah": "Eindhoven (EIN) →\nLondon (STN)",
    "direkt": "Direct"
  },
  {
    "fiyat": "18.64 USD",
    "havayolu": "Ryanair",
    "zamanaralik": "8:30pm -\n9:40pm",
    "tarih": "15 Ağustos 2024, Perşembe",
    "sure": "1 saat 10 dakika",
    "guzergah": "Zagreb (ZAG) →\nPodgorica (TGD)",
    "direkt": "Direct"
  },
  {
    "fiyat": "18.70 USD",
    "havayolu": "Ryanair",
    "zamanaralik": "4:15pm -\n5:25pm",
    "tarih": "17 Ağustos 2024, Cumartesi",
    "sure": "1 saat 10 dakika",
    "guzergah": "Zagreb (ZAG) →\nPodgorica (TGD)",
    "direkt": "Direct"
  },
  {
    "fiyat": "18.72 USD",
    "havayolu": "Ryanair",
    "zamanaralik": "3:05pm -\n3:00pm",
    "tarih": "16 Ağustos 2024, Cuma",
    "sure": "0 saat 55 dakika",
    "guzergah": "Málaga (AGP) →\nNador (NDR)",
    "direkt": "Direct"
  },
  {
    "fiyat": "19.31 USD",
    "havayolu": "Ryanair",
    "zamanaralik": "1:00pm -\n2:10pm",
    "tarih": "16 Ağustos 2024, Cuma",
    "sure": "1 saat 10 dakika",
    "guzergah": "Zagreb (ZAG) →\nPodgorica (TGD)",
    "direkt": "Direct"
  },
  {
    "fiyat": "41 USD",
    "havayolu": "Iberia Airlines",
    "zamanaralik": "9:00am -\n9:05am",
    "tarih": "18 Ağustos 2024, Pazar",
    "sure": "1 saat 5 dakika",
    "guzergah": "Málaga (AGP) →\nTangier (TNG)",
    "direkt": "Direct"
  },
  {
    "fiyat": "41 USD",
    "havayolu": "Iberia Airlines",
    "zamanaralik": "12:25pm -\n12:30pm",
    "tarih": "5 Eylül 2024, Perşembe",
    "sure": "1 saat 5 dakika",
    "guzergah": "Málaga (AGP) →\nTangier (TNG)",
    "direkt": "Direct"
  },
  {
    "fiyat": "42 USD",
    "havayolu": "Iberia Airlines",
    "zamanaralik": "9:00am -\n9:05am",
    "tarih": "25 Ağustos 2024, Pazar",
    "sure": "1 saat 5 dakika",
    "guzergah": "Málaga (AGP) →\nTangier (TNG)",
    "direkt": "Direct"
  },
  {
    "fiyat": "42 USD",
    "havayolu": "Iberia Airlines",
    "zamanaralik": "8:40pm -\n8:45pm",
    "tarih": "31 Ağustos 2024, Cumartesi",
    "sure": "1 saat 5 dakika",
    "guzergah": "Málaga (AGP) →\nTangier (TNG)",
    "direkt": "Direct"
  },
  {
    "fiyat": "42 USD",
    "havayolu": "Iberia Airlines",
    "zamanaralik": "12:30pm -\n12:35pm",
    "tarih": "29 Ağustos 2024, Perşembe",
    "sure": "1 saat 5 dakika",
    "guzergah": "Málaga (AGP) →\nTangier (TNG)",
    "direkt": "Direct"
  },
  {
    "fiyat": "42 USD",
    "havayolu": "Iberia Airlines",
    "zamanaralik": "12:25pm -\n12:30pm",
    "tarih": "27 Ağustos 2024, Salı",
    "sure": "1 saat 5 dakika",
    "guzergah": "Málaga (AGP) →\nTangier (TNG)",
    "direkt": "Direct"
  },
  {
    "fiyat": "42 USD",
    "havayolu": "Iberia Airlines",
    "zamanaralik": "12:30pm -\n12:35pm",
    "tarih": "26 Ağustos 2024, Pazartesi",
    "sure": "1 saat 5 dakika",
    "guzergah": "Málaga (AGP) →\nTangier (TNG)",
    "direkt": "Direct"
  },
  {
    "fiyat": "43 USD",
    "havayolu": "British Airways",
    "zamanaralik": "9:20pm -\n9:45pm",
    "tarih": "8 Eylül 2024, Pazar",
    "sure": "1 saat 25 dakika",
    "guzergah": "Luxembourg (LUX) →\nLondon (LHR)",
    "direkt": "Direct"
  },
  {
    "fiyat": "45 USD",
    "havayolu": "Iberia Airlines",
    "zamanaralik": "12:25pm -\n12:30pm",
    "tarih": "7 Eylül 2024, Cumartesi",
    "sure": "1 saat 5 dakika",
    "guzergah": "Málaga (AGP) →\nTangier (TNG)",
    "direkt": "Direct"
  },
  {
    "fiyat": "46 USD",
    "havayolu": "Iberia Airlines",
    "zamanaralik": "9:00am -\n9:05am",
    "tarih": "1 Eylül 2024, Pazar",
    "sure": "1 saat 5 dakika",
    "guzergah": "Málaga (AGP) →\nTangier (TNG)",
    "direkt": "Direct"
  },
  {
    "fiyat": "162 USD",
    "havayolu": "Vueling",
    "zamanaralik": "6:30pm -\n7:45pm",
    "tarih": "12 Ağustos 2024, Pazartesi",
    "sure": "2 saat 15 dakika",
    "guzergah": "Barcelona (BCN) →\nLondon (LHR)",
    "direkt": "Direct"
  },
  {
    "fiyat": "176 USD",
    "havayolu": "Vueling",
    "zamanaralik": "7:50am -\n9:05am",
    "tarih": "12 Ağustos 2024, Pazartesi",
    "sure": "2 saat 15 dakika",
    "guzergah": "Barcelona (BCN) →\nLondon (LHR)",
    "direkt": "Direct"
  },
  {
    "fiyat": "229 USD",
    "havayolu": "Air Algerie",
    "zamanaralik": "4:45pm -\n4:30pm",
    "tarih": "17 Ağustos 2024, Cumartesi",
    "sure": "0 saat 45 dakika",
    "guzergah": "Palma, Majorca (PMI) →\nAlgiers (ALG)",
    "direkt": "Direct"
  },
  {
    "fiyat": "293 USD",
    "havayolu": "British Airways",
    "zamanaralik": "6:30pm -\n7:45pm",
    "tarih": "12 Ağustos 2024, Pazartesi",
    "sure": "2 saat 15 dakika",
    "guzergah": "Barcelona (BCN) →\nLondon (LHR)",
    "direkt": "Direct"
  }
]
